[
  {
    "id": "5199a380-78b4-469a-8ab6-ff4fd641ea19",
    "professional_id": "f9a7923a-5cab-4bb7-9ec8-7524a54046ba",
    "is_active": true,
    "requested_count": 3,
    "assigned_count": 0,
    "remaining_count": 3,
    "request_client_types": [],
    "request_modalities": [],
    "request_followup_types": [],
    "request_comment": "Des ados",
    "created_at": "2026-05-19T14:08:14.998586+00:00",
    "updated_at": "2026-05-19T14:08:14.998586+00:00"
  },
  {
    "id": "28764f5d-39eb-4bac-9f80-6163caa3c4ce",
    "professional_id": "d32a577c-7996-4f49-ae31-2486ee5811bd",
    "is_active": true,
    "requested_count": 3,
    "assigned_count": 3,
    "remaining_count": 0,
    "request_client_types": [],
    "request_modalities": [],
    "request_followup_types": [],
    "request_comment": "Des adultes santé mentale",
    "created_at": "2026-05-28T09:38:25.547867+00:00",
    "updated_at": "2026-05-28T09:38:25.547867+00:00"
  },
  {
    "id": "9228d97c-b658-47b9-91bf-eec90b1602ae",
    "professional_id": "d32a577c-7996-4f49-ae31-2486ee5811bd",
    "is_active": true,
    "requested_count": 3,
    "assigned_count": 3,
    "remaining_count": 0,
    "request_client_types": [],
    "request_modalities": [],
    "request_followup_types": [],
    "request_comment": null,
    "created_at": "2026-06-03T17:18:57.1742+00:00",
    "updated_at": "2026-06-03T17:18:57.1742+00:00"
  },
  {
    "id": "87117aa4-bd07-4566-939b-0add4b94faa0",
    "professional_id": "d32a577c-7996-4f49-ae31-2486ee5811bd",
    "is_active": true,
    "requested_count": 2,
    "assigned_count": 2,
    "remaining_count": 0,
    "request_client_types": [],
    "request_modalities": [],
    "request_followup_types": [],
    "request_comment": "Je veux seulement des adultes de plus de 21 ans",
    "created_at": "2026-06-08T15:22:17.932084+00:00",
    "updated_at": "2026-06-08T15:22:17.932084+00:00"
  },
  {
    "id": "4354dbca-9a67-41e1-9dbd-d8c3447e9fde",
    "professional_id": "fa53ace4-a6ba-40ed-a723-25529a1ada9f",
    "is_active": true,
    "requested_count": 3,
    "assigned_count": 3,
    "remaining_count": 0,
    "request_client_types": [],
    "request_modalities": [],
    "request_followup_types": [],
    "request_comment": "que des adultes",
    "created_at": "2026-05-19T14:15:47.135941+00:00",
    "updated_at": "2026-05-19T14:15:47.135941+00:00"
  },
  {
    "id": "63935711-1857-44d9-b627-0058eaa189c1",
    "professional_id": "fa53ace4-a6ba-40ed-a723-25529a1ada9f",
    "is_active": true,
    "requested_count": 2,
    "assigned_count": 2,
    "remaining_count": 0,
    "request_client_types": [],
    "request_modalities": [],
    "request_followup_types": [],
    "request_comment": "Adultes 40 ans et plus",
    "created_at": "2026-06-10T22:29:42.63049+00:00",
    "updated_at": "2026-06-10T22:29:42.63049+00:00"
  },
  {
    "id": "d85ab418-7c49-42c8-bf21-ac0ce177dafb",
    "professional_id": "d32a577c-7996-4f49-ae31-2486ee5811bd",
    "is_active": true,
    "requested_count": 2,
    "assigned_count": 3,
    "remaining_count": 0,
    "request_client_types": [],
    "request_modalities": [],
    "request_followup_types": [],
    "request_comment": "Enfant ou famille",
    "created_at": "2026-05-20T16:31:32.863669+00:00",
    "updated_at": "2026-05-20T16:31:32.863669+00:00"
  },
  {
    "id": "eae6a852-ffce-44bc-9a78-87e2f394605b",
    "professional_id": "d32a577c-7996-4f49-ae31-2486ee5811bd",
    "is_active": true,
    "requested_count": 2,
    "assigned_count": 2,
    "remaining_count": 0,
    "request_client_types": [],
    "request_modalities": [],
    "request_followup_types": [],
    "request_comment": null,
    "created_at": "2026-05-25T07:04:14.075162+00:00",
    "updated_at": "2026-05-25T07:04:14.075162+00:00"
  },
  {
    "id": "8608fa8d-a92a-4911-b38d-02f0cc5d14ab",
    "professional_id": "d32a577c-7996-4f49-ae31-2486ee5811bd",
    "is_active": true,
    "requested_count": 2,
    "assigned_count": 2,
    "remaining_count": 0,
    "request_client_types": [],
    "request_modalities": [],
    "request_followup_types": [],
    "request_comment": "dsgnlsgdi`gds",
    "created_at": "2026-05-25T07:12:34.297424+00:00",
    "updated_at": "2026-05-25T07:12:34.297424+00:00"
  },
  {
    "id": "f2b4c73d-9cbb-49f0-a5ec-66abddba2750",
    "professional_id": "d32a577c-7996-4f49-ae31-2486ee5811bd",
    "is_active": true,
    "requested_count": 2,
    "assigned_count": 2,
    "remaining_count": 0,
    "request_client_types": [],
    "request_modalities": [],
    "request_followup_types": [],
    "request_comment": "Des enfants ou familles",
    "created_at": "2026-05-25T15:19:35.20482+00:00",
    "updated_at": "2026-05-25T15:19:35.20482+00:00"
  },
  {
    "id": "95751cde-3aab-40b4-989d-ccf49f5c1050",
    "professional_id": "fa53ace4-a6ba-40ed-a723-25529a1ada9f",
    "is_active": true,
    "requested_count": 2,
    "assigned_count": 2,
    "remaining_count": 0,
    "request_client_types": [],
    "request_modalities": [],
    "request_followup_types": [],
    "request_comment": "ados 14 à 18 ans",
    "created_at": "2026-06-11T18:46:22.43761+00:00",
    "updated_at": "2026-06-11T18:46:22.43761+00:00"
  },
  {
    "id": "eb1caf5d-3cac-4a5b-b4b2-d800119c18a9",
    "professional_id": "fa53ace4-a6ba-40ed-a723-25529a1ada9f",
    "is_active": false,
    "requested_count": 0,
    "assigned_count": 0,
    "remaining_count": 0,
    "request_client_types": [],
    "request_modalities": [],
    "request_followup_types": [],
    "request_comment": null,
    "created_at": "2026-06-12T00:42:21.59864+00:00",
    "updated_at": "2026-06-12T00:42:21.59864+00:00"
  },
  {
    "id": "06963be1-f7f3-4898-915f-1dbd8623b5b3",
    "professional_id": "fa53ace4-a6ba-40ed-a723-25529a1ada9f",
    "is_active": false,
    "requested_count": 0,
    "assigned_count": 0,
    "remaining_count": 0,
    "request_client_types": [],
    "request_modalities": [],
    "request_followup_types": [],
    "request_comment": null,
    "created_at": "2026-06-12T17:04:25.192866+00:00",
    "updated_at": "2026-06-12T17:04:25.192866+00:00"
  },
  {
    "id": "5cb1e473-0f37-4ed5-b8af-9aea3c76a3c8",
    "professional_id": "fa53ace4-a6ba-40ed-a723-25529a1ada9f",
    "is_active": false,
    "requested_count": 0,
    "assigned_count": 0,
    "remaining_count": 0,
    "request_client_types": [],
    "request_modalities": [],
    "request_followup_types": [],
    "request_comment": null,
    "created_at": "2026-06-12T18:38:15.664126+00:00",
    "updated_at": "2026-06-12T18:38:15.664126+00:00"
  },
  {
    "id": "9189f3cf-3fa3-4085-9532-c16f8c44b009",
    "professional_id": "fa53ace4-a6ba-40ed-a723-25529a1ada9f",
    "is_active": true,
    "requested_count": 2,
    "assigned_count": 0,
    "remaining_count": 2,
    "request_client_types": [],
    "request_modalities": [],
    "request_followup_types": [],
    "request_comment": null,
    "created_at": "2026-06-12T19:14:08.330447+00:00",
    "updated_at": "2026-06-12T19:14:08.330447+00:00"
  }
]